pyqueuex/__init__.py
pyqueuex/exceptions.py
pyqueuex/job.py
pyqueuex/queuex.py
pyqueuex/strategies.py
pyqueuex/types.py
pyqueuex/utils.py
pyqueuex/worker.py
pyqueuex-0.1.0.dist-info/METADATA
pyqueuex-0.1.0.dist-info/WHEEL
pyqueuex-0.1.0.dist-info/licenses/LICENSE
pyqueuex-0.1.0.dist-info/RECORD
