Metadata-Version: 2.4
Name: pyqueuex
Version: 0.1.0
Summary: A powerful, feature-rich job queue system for Python with advanced retry strategies, job chaining, and intelligent job processing.
Project-URL: Homepage, https://github.com/yourusername/pyqueuex
Project-URL: Repository, https://github.com/yourusername/pyqueuex.git
Project-URL: Issues, https://github.com/yourusername/pyqueuex/issues
Project-URL: Documentation, https://pyqueuex.readthedocs.io/
Author-email: Avijit <avijitsen24.me@gmail.com>
License: MIT License
License-File: LICENSE
Classifier: License :: OSI Approved :: MIT License
Classifier: Operating System :: OS Independent
Classifier: Programming Language :: Python :: 3
Requires-Python: >=3.8
Requires-Dist: redis>=5.0.0
